simulation/__init__.py
simulation/action.py
simulation/avatar_state.py
simulation/direction.py
simulation/event.py
simulation/location.py
simulation/world_map.py
aimmo_game_worker_simulation_test-0.0.1a0.dist-info/METADATA
aimmo_game_worker_simulation_test-0.0.1a0.dist-info/WHEEL
aimmo_game_worker_simulation_test-0.0.1a0.dist-info/top_level.txt
aimmo_game_worker_simulation_test-0.0.1a0.dist-info/RECORD
