Metadata-Version: 2.1
Name: aimmo-game-worker-simulation-test
Version: 0.0.1a0
Summary: UNKNOWN
Home-page: UNKNOWN
Author: UNKNOWN
Author-email: UNKNOWN
License: UNKNOWN
Platform: UNKNOWN
Requires-Dist: flask
Requires-Dist: requests
